{"file":"05.csv","job_id":"00155","provider_hints":{"amap":{"correction":"denoise=1,mapmatch=1,attribute=1,threshold=20,mode=driving","recoup":1,"gap":50},"baidu":{"is_processed":1,"process_option":"denoise_grade=5,need_mapmatch=1,transport_mode=driving","supplement_mode":"driving","coord_type_output":"gcj02"}},"source":{"start_time":"2026-01-06 07:30:23","end_time":"2026-01-06 07:32:13","raw_points":5,"moving_points":5,"raw_distance_m":522.7,"mileage_delta_m":600.0},"points":[{"lon":120.158897,"lat":30.260653,"locatetime":1767655823000,"time":"2026-01-06 07:30:23","speed":41.5,"mileage":237491.4},{"lon":120.155838,"lat":30.260412,"locatetime":1767655853000,"time":"2026-01-06 07:30:53","speed":14.5,"mileage":237491.7},{"lon":120.155678,"lat":30.260759,"locatetime":1767655863000,"time":"2026-01-06 07:31:03","speed":29.5,"mileage":237491.8},{"lon":120.156166,"lat":30.261486,"locatetime":1767655913000,"time":"2026-01-06 07:31:53","speed":25.0,"mileage":237491.9},{"lon":120.157005,"lat":30.261074,"locatetime":1767655933000,"time":"2026-01-06 07:32:13","speed":28.5,"mileage":237492.0}]}