{"file":"05.csv","job_id":"00217","provider_hints":{"amap":{"correction":"denoise=1,mapmatch=1,attribute=1,threshold=20,mode=driving","recoup":1,"gap":50},"baidu":{"is_processed":1,"process_option":"denoise_grade=5,need_mapmatch=1,transport_mode=driving","supplement_mode":"driving","coord_type_output":"gcj02"}},"source":{"start_time":"2026-01-08 07:04:13","end_time":"2026-01-08 07:15:43","raw_points":9,"moving_points":9,"raw_distance_m":1914.1,"mileage_delta_m":2200.0},"points":[{"lon":120.197853,"lat":30.269779,"locatetime":1767827053000,"time":"2026-01-08 07:04:13","speed":27.5,"mileage":237793.7},{"lon":120.198753,"lat":30.269848,"locatetime":1767827103000,"time":"2026-01-08 07:05:03","speed":6.0,"mileage":237793.8},{"lon":120.198975,"lat":30.270519,"locatetime":1767827133000,"time":"2026-01-08 07:05:33","speed":9.5,"mileage":237793.9},{"lon":120.198898,"lat":30.272717,"locatetime":1767827203000,"time":"2026-01-08 07:06:43","speed":8.0,"mileage":237794.2},{"lon":120.201683,"lat":30.273104,"locatetime":1767827283000,"time":"2026-01-08 07:08:03","speed":7.0,"mileage":237794.5},{"lon":120.208954,"lat":30.273148,"locatetime":1767827553000,"time":"2026-01-08 07:12:33","speed":18.0,"mileage":237795.2},{"lon":120.207481,"lat":30.276373,"locatetime":1767827703000,"time":"2026-01-08 07:15:03","speed":18.0,"mileage":237795.7},{"lon":120.206497,"lat":30.276268,"locatetime":1767827723000,"time":"2026-01-08 07:15:23","speed":14.5,"mileage":237795.8},{"lon":120.206406,"lat":30.27676,"locatetime":1767827743000,"time":"2026-01-08 07:15:43","speed":14.0,"mileage":237795.9}]}