{"file":"05.csv","job_id":"00993","provider_hints":{"amap":{"correction":"denoise=1,mapmatch=1,attribute=1,threshold=20,mode=driving","recoup":1,"gap":50},"baidu":{"is_processed":1,"process_option":"denoise_grade=5,need_mapmatch=1,transport_mode=driving","supplement_mode":"driving","coord_type_output":"gcj02"}},"source":{"start_time":"2026-02-01 13:00:21","end_time":"2026-02-01 13:13:01","raw_points":8,"moving_points":8,"raw_distance_m":2976.7,"mileage_delta_m":3300.0},"points":[{"lon":120.196358,"lat":30.26582,"locatetime":1769922021000,"time":"2026-02-01 13:00:21","speed":15.5,"mileage":241571.1},{"lon":120.195953,"lat":30.260384,"locatetime":1769922201000,"time":"2026-02-01 13:03:21","speed":4.5,"mileage":241571.9},{"lon":120.194832,"lat":30.260336,"locatetime":1769922221000,"time":"2026-02-01 13:03:41","speed":24.0,"mileage":241572.0},{"lon":120.193443,"lat":30.25988,"locatetime":1769922311000,"time":"2026-02-01 13:05:11","speed":1.5,"mileage":241572.1},{"lon":120.188499,"lat":30.259804,"locatetime":1769922461000,"time":"2026-02-01 13:07:41","speed":18.0,"mileage":241572.6},{"lon":120.17968,"lat":30.260391,"locatetime":1769922541000,"time":"2026-02-01 13:09:01","speed":40.0,"mileage":241573.6},{"lon":120.172455,"lat":30.260391,"locatetime":1769922681000,"time":"2026-02-01 13:11:21","speed":4.5,"mileage":241574.3},{"lon":120.171478,"lat":30.260029,"locatetime":1769922781000,"time":"2026-02-01 13:13:01","speed":29.0,"mileage":241574.4}]}