{"file":"05.csv","job_id":"01229","provider_hints":{"amap":{"correction":"denoise=1,mapmatch=1,attribute=1,threshold=20,mode=driving","recoup":1,"gap":50},"baidu":{"is_processed":1,"process_option":"denoise_grade=5,need_mapmatch=1,transport_mode=driving","supplement_mode":"driving","coord_type_output":"gcj02"}},"source":{"start_time":"2026-02-08 15:49:53","end_time":"2026-02-08 16:01:23","raw_points":7,"moving_points":7,"raw_distance_m":2480.0,"mileage_delta_m":2700.0},"points":[{"lon":120.197083,"lat":30.266079,"locatetime":1770536993000,"time":"2026-02-08 15:49:53","speed":4.5,"mileage":242710.0},{"lon":120.196823,"lat":30.266197,"locatetime":1770537023000,"time":"2026-02-08 15:50:23","speed":9.5,"mileage":242710.0},{"lon":120.196175,"lat":30.265753,"locatetime":1770537123000,"time":"2026-02-08 15:52:03","speed":21.0,"mileage":242710.1},{"lon":120.196335,"lat":30.260468,"locatetime":1770537213000,"time":"2026-02-08 15:53:33","speed":4.5,"mileage":242710.8},{"lon":120.196106,"lat":30.260185,"locatetime":1770537273000,"time":"2026-02-08 15:54:33","speed":13.0,"mileage":242710.8},{"lon":120.190903,"lat":30.259865,"locatetime":1770537433000,"time":"2026-02-08 15:57:13","speed":29.0,"mileage":242711.3},{"lon":120.177956,"lat":30.260435,"locatetime":1770537683000,"time":"2026-02-08 16:01:23","speed":8.5,"mileage":242712.7}]}