{"file":"05.csv","job_id":"01766","provider_hints":{"amap":{"correction":"denoise=1,mapmatch=1,attribute=1,threshold=20,mode=driving","recoup":1,"gap":50},"baidu":{"is_processed":1,"process_option":"denoise_grade=5,need_mapmatch=1,transport_mode=driving","supplement_mode":"driving","coord_type_output":"gcj02"}},"source":{"start_time":"2026-02-24 11:38:47","end_time":"2026-02-24 11:42:27","raw_points":5,"moving_points":5,"raw_distance_m":577.9,"mileage_delta_m":700.0},"points":[{"lon":120.167786,"lat":30.240025,"locatetime":1771904327000,"time":"2026-02-24 11:38:47","speed":21.0,"mileage":245467.4},{"lon":120.167503,"lat":30.240192,"locatetime":1771904337000,"time":"2026-02-24 11:38:57","speed":27.0,"mileage":245467.5},{"lon":120.167107,"lat":30.242435,"locatetime":1771904427000,"time":"2026-02-24 11:40:27","speed":26.5,"mileage":245468.0},{"lon":120.167397,"lat":30.244404,"locatetime":1771904527000,"time":"2026-02-24 11:42:07","speed":16.0,"mileage":245468.0},{"lon":120.167015,"lat":30.244961,"locatetime":1771904547000,"time":"2026-02-24 11:42:27","speed":3.5,"mileage":245468.1}]}