{"file":"05.csv","job_id":"02721","provider_hints":{"amap":{"correction":"denoise=1,mapmatch=1,attribute=1,threshold=20,mode=driving","recoup":1,"gap":50},"baidu":{"is_processed":1,"process_option":"denoise_grade=5,need_mapmatch=1,transport_mode=driving","supplement_mode":"driving","coord_type_output":"gcj02"}},"source":{"start_time":"2026-03-25 08:24:36","end_time":"2026-03-25 08:37:36","raw_points":9,"moving_points":9,"raw_distance_m":3462.2,"mileage_delta_m":3800.0},"points":[{"lon":120.199142,"lat":30.2726,"locatetime":1774398276000,"time":"2026-03-25 08:24:36","speed":14.5,"mileage":250299.0},{"lon":120.199699,"lat":30.266376,"locatetime":1774398546000,"time":"2026-03-25 08:29:06","speed":7.5,"mileage":250299.8},{"lon":120.195946,"lat":30.2658,"locatetime":1774398656000,"time":"2026-03-25 08:30:56","speed":34.5,"mileage":250300.2},{"lon":120.196434,"lat":30.264879,"locatetime":1774398686000,"time":"2026-03-25 08:31:26","speed":45.0,"mileage":250300.4},{"lon":120.196625,"lat":30.261076,"locatetime":1774398726000,"time":"2026-03-25 08:32:06","speed":25.5,"mileage":250300.9},{"lon":120.196457,"lat":30.260689,"locatetime":1774398736000,"time":"2026-03-25 08:32:16","speed":18.0,"mileage":250300.9},{"lon":120.194061,"lat":30.259859,"locatetime":1774398786000,"time":"2026-03-25 08:33:06","speed":22.5,"mileage":250301.1},{"lon":120.185249,"lat":30.25997,"locatetime":1774398906000,"time":"2026-03-25 08:35:06","speed":46.0,"mileage":250302.0},{"lon":120.177711,"lat":30.260424,"locatetime":1774399056000,"time":"2026-03-25 08:37:36","speed":14.5,"mileage":250302.8}]}