{"file":"05.csv","job_id":"04584","provider_hints":{"amap":{"correction":"denoise=1,mapmatch=1,attribute=1,threshold=20,mode=driving","recoup":1,"gap":50},"baidu":{"is_processed":1,"process_option":"denoise_grade=5,need_mapmatch=1,transport_mode=driving","supplement_mode":"driving","coord_type_output":"gcj02"}},"source":{"start_time":"2026-05-18 13:09:59","end_time":"2026-05-18 13:13:19","raw_points":5,"moving_points":5,"raw_distance_m":552.4,"mileage_delta_m":700.0},"points":[{"lon":120.208527,"lat":30.273048,"locatetime":1779080999000,"time":"2026-05-18 13:09:59","speed":10.5,"mileage":259280.6},{"lon":120.208733,"lat":30.273268,"locatetime":1779081009000,"time":"2026-05-18 13:10:09","speed":28.5,"mileage":259280.7},{"lon":120.207214,"lat":30.27632,"locatetime":1779081079000,"time":"2026-05-18 13:11:19","speed":6.0,"mileage":259281.1},{"lon":120.206291,"lat":30.276592,"locatetime":1779081129000,"time":"2026-05-18 13:12:09","speed":14.5,"mileage":259281.2},{"lon":120.206459,"lat":30.277092,"locatetime":1779081199000,"time":"2026-05-18 13:13:19","speed":2.0,"mileage":259281.3}]}