{"file":"04.csv","job_id":"01021","provider_hints":{"amap":{"correction":"denoise=1,mapmatch=1,attribute=1,threshold=20,mode=driving","recoup":1,"gap":50},"baidu":{"is_processed":1,"process_option":"denoise_grade=5,need_mapmatch=1,transport_mode=driving","supplement_mode":"driving","coord_type_output":"gcj02"}},"source":{"start_time":"2026-02-11 11:22:51","end_time":"2026-02-11 11:27:31","raw_points":6,"moving_points":6,"raw_distance_m":1750.2,"mileage_delta_m":1900.0},"points":[{"lon":120.218727,"lat":30.273258,"locatetime":1770780171000,"time":"2026-02-11 11:22:51","speed":12.0,"mileage":234476.0},{"lon":120.216476,"lat":30.276085,"locatetime":1770780231000,"time":"2026-02-11 11:23:51","speed":25.0,"mileage":234476.4},{"lon":120.209282,"lat":30.272881,"locatetime":1770780311000,"time":"2026-02-11 11:25:11","speed":12.5,"mileage":234477.3},{"lon":120.207268,"lat":30.276293,"locatetime":1770780391000,"time":"2026-02-11 11:26:31","speed":6.5,"mileage":234477.7},{"lon":120.206238,"lat":30.27626,"locatetime":1770780411000,"time":"2026-02-11 11:26:51","speed":12.5,"mileage":234477.9},{"lon":120.20623,"lat":30.276859,"locatetime":1770780451000,"time":"2026-02-11 11:27:31","speed":5.5,"mileage":234477.9}]}