{"file":"04.csv","job_id":"01221","provider_hints":{"amap":{"correction":"denoise=1,mapmatch=1,attribute=1,threshold=20,mode=driving","recoup":1,"gap":50},"baidu":{"is_processed":1,"process_option":"denoise_grade=5,need_mapmatch=1,transport_mode=driving","supplement_mode":"driving","coord_type_output":"gcj02"}},"source":{"start_time":"2026-02-27 14:59:30","end_time":"2026-02-27 15:03:50","raw_points":5,"moving_points":5,"raw_distance_m":1242.4,"mileage_delta_m":1400.0},"points":[{"lon":120.209831,"lat":30.266312,"locatetime":1772175570000,"time":"2026-02-27 14:59:30","speed":14.0,"mileage":235427.2},{"lon":120.212677,"lat":30.267408,"locatetime":1772175640000,"time":"2026-02-27 15:00:40","speed":32.5,"mileage":235427.6},{"lon":120.219482,"lat":30.271675,"locatetime":1772175730000,"time":"2026-02-27 15:02:10","speed":19.0,"mileage":235428.4},{"lon":120.219772,"lat":30.272057,"locatetime":1772175820000,"time":"2026-02-27 15:03:40","speed":26.5,"mileage":235428.5},{"lon":120.21933,"lat":30.272717,"locatetime":1772175830000,"time":"2026-02-27 15:03:50","speed":27.5,"mileage":235428.6}]}