{"file":"04.csv","job_id":"02051","provider_hints":{"amap":{"correction":"denoise=1,mapmatch=1,attribute=1,threshold=20,mode=driving","recoup":1,"gap":50},"baidu":{"is_processed":1,"process_option":"denoise_grade=5,need_mapmatch=1,transport_mode=driving","supplement_mode":"driving","coord_type_output":"gcj02"}},"source":{"start_time":"2026-04-02 15:56:07","end_time":"2026-04-02 16:02:07","raw_points":7,"moving_points":7,"raw_distance_m":1570.1,"mileage_delta_m":1800.0},"points":[{"lon":120.209526,"lat":30.263613,"locatetime":1775116567000,"time":"2026-04-02 15:56:07","speed":12.5,"mileage":239418.6},{"lon":120.209877,"lat":30.264624,"locatetime":1775116597000,"time":"2026-04-02 15:56:37","speed":18.0,"mileage":239418.8},{"lon":120.209755,"lat":30.266373,"locatetime":1775116667000,"time":"2026-04-02 15:57:47","speed":15.5,"mileage":239419.0},{"lon":120.212692,"lat":30.267733,"locatetime":1775116747000,"time":"2026-04-02 15:59:07","speed":21.0,"mileage":239419.4},{"lon":120.219109,"lat":30.271769,"locatetime":1775116837000,"time":"2026-04-02 16:00:37","speed":5.0,"mileage":239420.2},{"lon":120.219383,"lat":30.272491,"locatetime":1775116917000,"time":"2026-04-02 16:01:57","speed":39.0,"mileage":239420.3},{"lon":120.218857,"lat":30.273172,"locatetime":1775116927000,"time":"2026-04-02 16:02:07","speed":20.5,"mileage":239420.4}]}