{"file":"04.csv","job_id":"02563","provider_hints":{"amap":{"correction":"denoise=1,mapmatch=1,attribute=1,threshold=20,mode=driving","recoup":1,"gap":50},"baidu":{"is_processed":1,"process_option":"denoise_grade=5,need_mapmatch=1,transport_mode=driving","supplement_mode":"driving","coord_type_output":"gcj02"}},"source":{"start_time":"2026-04-26 08:31:15","end_time":"2026-04-26 08:40:15","raw_points":10,"moving_points":10,"raw_distance_m":2692.5,"mileage_delta_m":2900.0},"points":[{"lon":120.206223,"lat":30.276917,"locatetime":1777163475000,"time":"2026-04-26 08:31:15","speed":17.0,"mileage":241798.0},{"lon":120.20639,"lat":30.277201,"locatetime":1777163495000,"time":"2026-04-26 08:31:35","speed":8.0,"mileage":241798.0},{"lon":120.207336,"lat":30.276712,"locatetime":1777163585000,"time":"2026-04-26 08:33:05","speed":15.5,"mileage":241798.1},{"lon":120.207771,"lat":30.276873,"locatetime":1777163595000,"time":"2026-04-26 08:33:15","speed":21.0,"mileage":241798.2},{"lon":120.213631,"lat":30.279749,"locatetime":1777163735000,"time":"2026-04-26 08:35:35","speed":28.0,"mileage":241798.9},{"lon":120.217873,"lat":30.275066,"locatetime":1777163865000,"time":"2026-04-26 08:37:45","speed":21.0,"mileage":241799.6},{"lon":120.221039,"lat":30.276684,"locatetime":1777163905000,"time":"2026-04-26 08:38:25","speed":20.5,"mileage":241800.0},{"lon":120.223305,"lat":30.274967,"locatetime":1777163945000,"time":"2026-04-26 08:39:05","speed":22.5,"mileage":241800.4},{"lon":120.220314,"lat":30.272087,"locatetime":1777163985000,"time":"2026-04-26 08:39:45","speed":18.0,"mileage":241800.8},{"lon":120.21936,"lat":30.272844,"locatetime":1777164015000,"time":"2026-04-26 08:40:15","speed":14.0,"mileage":241800.9}]}