{"file":"03.csv","job_id":"00351","provider_hints":{"amap":{"correction":"denoise=1,mapmatch=1,attribute=1,threshold=20,mode=driving","recoup":1,"gap":50},"baidu":{"is_processed":1,"process_option":"denoise_grade=5,need_mapmatch=1,transport_mode=driving","supplement_mode":"driving","coord_type_output":"gcj02"}},"source":{"start_time":"2026-01-14 06:17:25","end_time":"2026-01-14 06:20:25","raw_points":7,"moving_points":7,"raw_distance_m":512.3,"mileage_delta_m":800.0},"points":[{"lon":120.242943,"lat":30.308826,"locatetime":1768342645000,"time":"2026-01-14 06:17:25","speed":19.0,"mileage":194715.6},{"lon":120.242752,"lat":30.309057,"locatetime":1768342695000,"time":"2026-01-14 06:18:15","speed":2.5,"mileage":194715.7},{"lon":120.240654,"lat":30.309158,"locatetime":1768342745000,"time":"2026-01-14 06:19:05","speed":29.0,"mileage":194715.9},{"lon":120.240166,"lat":30.308968,"locatetime":1768342755000,"time":"2026-01-14 06:19:15","speed":20.0,"mileage":194716.0},{"lon":120.240067,"lat":30.310247,"locatetime":1768342795000,"time":"2026-01-14 06:19:55","speed":24.5,"mileage":194716.3},{"lon":120.240448,"lat":30.31032,"locatetime":1768342815000,"time":"2026-01-14 06:20:15","speed":12.5,"mileage":194716.4},{"lon":120.240555,"lat":30.310738,"locatetime":1768342825000,"time":"2026-01-14 06:20:25","speed":5.0,"mileage":194716.4}]}