{"file":"03.csv","job_id":"03212","provider_hints":{"amap":{"correction":"denoise=1,mapmatch=1,attribute=1,threshold=20,mode=driving","recoup":1,"gap":50},"baidu":{"is_processed":1,"process_option":"denoise_grade=5,need_mapmatch=1,transport_mode=driving","supplement_mode":"driving","coord_type_output":"gcj02"}},"source":{"start_time":"2026-05-13 08:36:06","end_time":"2026-05-13 08:38:36","raw_points":5,"moving_points":5,"raw_distance_m":569.5,"mileage_delta_m":600.0},"points":[{"lon":120.240242,"lat":30.311602,"locatetime":1778632566000,"time":"2026-05-13 08:36:06","speed":12.5,"mileage":206277.1},{"lon":120.242241,"lat":30.311636,"locatetime":1778632596000,"time":"2026-05-13 08:36:36","speed":23.0,"mileage":206277.3},{"lon":120.24337,"lat":30.312029,"locatetime":1778632636000,"time":"2026-05-13 08:37:16","speed":28.0,"mileage":206277.5},{"lon":120.244987,"lat":30.313074,"locatetime":1778632686000,"time":"2026-05-13 08:38:06","speed":10.0,"mileage":206277.7},{"lon":120.245682,"lat":30.313034,"locatetime":1778632716000,"time":"2026-05-13 08:38:36","speed":20.0,"mileage":206277.7}]}