{"file":"01.csv","job_id":"00330","provider_hints":{"amap":{"correction":"denoise=1,mapmatch=1,attribute=1,threshold=20,mode=driving","recoup":1,"gap":50},"baidu":{"is_processed":1,"process_option":"denoise_grade=5,need_mapmatch=1,transport_mode=driving","supplement_mode":"driving","coord_type_output":"gcj02"}},"source":{"start_time":"2026-01-13 14:54:34","end_time":"2026-01-13 15:00:44","raw_points":6,"moving_points":6,"raw_distance_m":534.2,"mileage_delta_m":400.0},"points":[{"lon":120.249153,"lat":30.30867,"locatetime":1768287274000,"time":"2026-01-13 14:54:34","speed":12.0,"mileage":191142.4},{"lon":120.24836,"lat":30.309912,"locatetime":1768287284000,"time":"2026-01-13 14:54:44","speed":21.5,"mileage":191142.4},{"lon":120.24884,"lat":30.310087,"locatetime":1768287304000,"time":"2026-01-13 14:55:04","speed":12.5,"mileage":191142.5},{"lon":120.249298,"lat":30.309036,"locatetime":1768287334000,"time":"2026-01-13 14:55:34","speed":9.0,"mileage":191142.7},{"lon":120.248787,"lat":30.309015,"locatetime":1768287344000,"time":"2026-01-13 14:55:44","speed":17.5,"mileage":191142.7},{"lon":120.247513,"lat":30.309835,"locatetime":1768287644000,"time":"2026-01-13 15:00:44","speed":11.5,"mileage":191142.8}]}