{"file":"01.csv","job_id":"01573","provider_hints":{"amap":{"correction":"denoise=1,mapmatch=1,attribute=1,threshold=20,mode=driving","recoup":1,"gap":50},"baidu":{"is_processed":1,"process_option":"denoise_grade=5,need_mapmatch=1,transport_mode=driving","supplement_mode":"driving","coord_type_output":"gcj02"}},"source":{"start_time":"2026-03-03 17:50:25","end_time":"2026-03-03 17:56:55","raw_points":6,"moving_points":6,"raw_distance_m":1610.7,"mileage_delta_m":1700.0},"points":[{"lon":120.2668,"lat":30.312834,"locatetime":1772531425000,"time":"2026-03-03 17:50:25","speed":34.5,"mileage":196410.3},{"lon":120.262146,"lat":30.312807,"locatetime":1772531595000,"time":"2026-03-03 17:53:15","speed":25.5,"mileage":196410.8},{"lon":120.261963,"lat":30.31049,"locatetime":1772531625000,"time":"2026-03-03 17:53:45","speed":22.0,"mileage":196411.1},{"lon":120.261703,"lat":30.310265,"locatetime":1772531635000,"time":"2026-03-03 17:53:55","speed":24.5,"mileage":196411.1},{"lon":120.255829,"lat":30.310268,"locatetime":1772531765000,"time":"2026-03-03 17:56:05","speed":27.0,"mileage":196411.7},{"lon":120.252739,"lat":30.309574,"locatetime":1772531815000,"time":"2026-03-03 17:56:55","speed":24.5,"mileage":196412.0}]}