{"file":"02.csv","job_id":"00427","provider_hints":{"amap":{"correction":"denoise=1,mapmatch=1,attribute=1,threshold=20,mode=driving","recoup":1,"gap":50},"baidu":{"is_processed":1,"process_option":"denoise_grade=5,need_mapmatch=1,transport_mode=driving","supplement_mode":"driving","coord_type_output":"gcj02"}},"source":{"start_time":"2026-01-13 13:51:01","end_time":"2026-01-13 13:57:41","raw_points":8,"moving_points":8,"raw_distance_m":1636.4,"mileage_delta_m":1900.0},"points":[{"lon":120.195763,"lat":30.260176,"locatetime":1768283461000,"time":"2026-01-13 13:51:01","speed":12.5,"mileage":217523.1},{"lon":120.195839,"lat":30.2654,"locatetime":1768283611000,"time":"2026-01-13 13:53:31","speed":22.5,"mileage":217523.8},{"lon":120.196289,"lat":30.266163,"locatetime":1768283631000,"time":"2026-01-13 13:53:51","speed":44.5,"mileage":217524.0},{"lon":120.196022,"lat":30.269279,"locatetime":1768283691000,"time":"2026-01-13 13:54:51","speed":19.5,"mileage":217524.3},{"lon":120.198746,"lat":30.269739,"locatetime":1768283761000,"time":"2026-01-13 13:56:01","speed":11.5,"mileage":217524.6},{"lon":120.199005,"lat":30.270599,"locatetime":1768283801000,"time":"2026-01-13 13:56:41","speed":19.5,"mileage":217524.7},{"lon":120.198891,"lat":30.272594,"locatetime":1768283841000,"time":"2026-01-13 13:57:21","speed":5.0,"mileage":217525.0},{"lon":120.199097,"lat":30.272736,"locatetime":1768283861000,"time":"2026-01-13 13:57:41","speed":24.5,"mileage":217525.0}]}