{"file":"02.csv","job_id":"01967","provider_hints":{"amap":{"correction":"denoise=1,mapmatch=1,attribute=1,threshold=20,mode=driving","recoup":1,"gap":50},"baidu":{"is_processed":1,"process_option":"denoise_grade=5,need_mapmatch=1,transport_mode=driving","supplement_mode":"driving","coord_type_output":"gcj02"}},"source":{"start_time":"2026-03-06 15:26:13","end_time":"2026-03-06 15:31:13","raw_points":6,"moving_points":6,"raw_distance_m":1084.1,"mileage_delta_m":1200.0},"points":[{"lon":120.20266,"lat":30.272945,"locatetime":1772781973000,"time":"2026-03-06 15:26:13","speed":24.0,"mileage":225281.2},{"lon":120.208328,"lat":30.273149,"locatetime":1772782113000,"time":"2026-03-06 15:28:33","speed":3.0,"mileage":225281.7},{"lon":120.208977,"lat":30.273485,"locatetime":1772782143000,"time":"2026-03-06 15:29:03","speed":39.0,"mileage":225281.9},{"lon":120.207214,"lat":30.276497,"locatetime":1772782233000,"time":"2026-03-06 15:30:33","speed":24.5,"mileage":225282.3},{"lon":120.206566,"lat":30.276363,"locatetime":1772782243000,"time":"2026-03-06 15:30:43","speed":2.0,"mileage":225282.3},{"lon":120.206413,"lat":30.276571,"locatetime":1772782273000,"time":"2026-03-06 15:31:13","speed":24.0,"mileage":225282.4}]}