{"file":"02.csv","job_id":"02594","provider_hints":{"amap":{"correction":"denoise=1,mapmatch=1,attribute=1,threshold=20,mode=driving","recoup":1,"gap":50},"baidu":{"is_processed":1,"process_option":"denoise_grade=5,need_mapmatch=1,transport_mode=driving","supplement_mode":"driving","coord_type_output":"gcj02"}},"source":{"start_time":"2026-03-24 07:24:27","end_time":"2026-03-24 07:39:17","raw_points":10,"moving_points":10,"raw_distance_m":3182.6,"mileage_delta_m":3500.0},"points":[{"lon":120.199173,"lat":30.272596,"locatetime":1774308267000,"time":"2026-03-24 07:24:27","speed":26.5,"mileage":228203.4},{"lon":120.199554,"lat":30.266596,"locatetime":1774308407000,"time":"2026-03-24 07:26:47","speed":16.5,"mileage":228204.1},{"lon":120.199043,"lat":30.266293,"locatetime":1774308427000,"time":"2026-03-24 07:27:07","speed":34.0,"mileage":228204.2},{"lon":120.196747,"lat":30.265987,"locatetime":1774308477000,"time":"2026-03-24 07:27:57","speed":4.0,"mileage":228204.4},{"lon":120.196457,"lat":30.265631,"locatetime":1774308527000,"time":"2026-03-24 07:28:47","speed":24.0,"mileage":228204.5},{"lon":120.195709,"lat":30.261078,"locatetime":1774308737000,"time":"2026-03-24 07:32:17","speed":6.0,"mileage":228205.1},{"lon":120.195824,"lat":30.260357,"locatetime":1774308807000,"time":"2026-03-24 07:33:27","speed":1.5,"mileage":228205.2},{"lon":120.194344,"lat":30.259972,"locatetime":1774308877000,"time":"2026-03-24 07:34:37","speed":1.5,"mileage":228205.3},{"lon":120.192093,"lat":30.259895,"locatetime":1774308907000,"time":"2026-03-24 07:35:07","speed":26.5,"mileage":228205.6},{"lon":120.179337,"lat":30.260368,"locatetime":1774309157000,"time":"2026-03-24 07:39:17","speed":22.0,"mileage":228206.9}]}