{"file":"02.csv","job_id":"02612","provider_hints":{"amap":{"correction":"denoise=1,mapmatch=1,attribute=1,threshold=20,mode=driving","recoup":1,"gap":50},"baidu":{"is_processed":1,"process_option":"denoise_grade=5,need_mapmatch=1,transport_mode=driving","supplement_mode":"driving","coord_type_output":"gcj02"}},"source":{"start_time":"2026-03-24 16:14:17","end_time":"2026-03-24 16:26:27","raw_points":5,"moving_points":5,"raw_distance_m":2153.1,"mileage_delta_m":2200.0},"points":[{"lon":120.165192,"lat":30.260553,"locatetime":1774340057000,"time":"2026-03-24 16:14:17","speed":2.5,"mileage":228302.2},{"lon":120.167618,"lat":30.260906,"locatetime":1774340237000,"time":"2026-03-24 16:17:17","speed":42.0,"mileage":228302.5},{"lon":120.174927,"lat":30.260489,"locatetime":1774340517000,"time":"2026-03-24 16:21:57","speed":28.0,"mileage":228303.2},{"lon":120.179825,"lat":30.26062,"locatetime":1774340727000,"time":"2026-03-24 16:25:27","speed":37.0,"mileage":228303.7},{"lon":120.187538,"lat":30.260147,"locatetime":1774340787000,"time":"2026-03-24 16:26:27","speed":43.0,"mileage":228304.4}]}