{"file":"02.csv","job_id":"03639","provider_hints":{"amap":{"correction":"denoise=1,mapmatch=1,attribute=1,threshold=20,mode=driving","recoup":1,"gap":50},"baidu":{"is_processed":1,"process_option":"denoise_grade=5,need_mapmatch=1,transport_mode=driving","supplement_mode":"driving","coord_type_output":"gcj02"}},"source":{"start_time":"2026-04-27 19:55:03","end_time":"2026-04-27 20:13:33","raw_points":9,"moving_points":9,"raw_distance_m":3871.9,"mileage_delta_m":4100.0},"points":[{"lon":120.155693,"lat":30.261707,"locatetime":1777290903000,"time":"2026-04-27 19:55:03","speed":1.5,"mileage":233194.5},{"lon":120.156944,"lat":30.260977,"locatetime":1777290943000,"time":"2026-04-27 19:55:43","speed":14.0,"mileage":233194.7},{"lon":120.160759,"lat":30.261072,"locatetime":1777291143000,"time":"2026-04-27 19:59:03","speed":39.0,"mileage":233195.1},{"lon":120.165535,"lat":30.260723,"locatetime":1777291303000,"time":"2026-04-27 20:01:43","speed":1.5,"mileage":233195.6},{"lon":120.169464,"lat":30.260902,"locatetime":1777291463000,"time":"2026-04-27 20:04:23","speed":6.0,"mileage":233196.0},{"lon":120.175217,"lat":30.260509,"locatetime":1777291603000,"time":"2026-04-27 20:06:43","speed":22.0,"mileage":233196.6},{"lon":120.179649,"lat":30.260733,"locatetime":1777291733000,"time":"2026-04-27 20:08:53","speed":35.0,"mileage":233197.0},{"lon":120.186142,"lat":30.260303,"locatetime":1777291783000,"time":"2026-04-27 20:09:43","speed":47.5,"mileage":233197.7},{"lon":120.195679,"lat":30.260344,"locatetime":1777292013000,"time":"2026-04-27 20:13:33","speed":4.5,"mileage":233198.6}]}