{"file":"02.csv","job_id":"03964","provider_hints":{"amap":{"correction":"denoise=1,mapmatch=1,attribute=1,threshold=20,mode=driving","recoup":1,"gap":50},"baidu":{"is_processed":1,"process_option":"denoise_grade=5,need_mapmatch=1,transport_mode=driving","supplement_mode":"driving","coord_type_output":"gcj02"}},"source":{"start_time":"2026-05-07 20:40:14","end_time":"2026-05-07 20:59:14","raw_points":7,"moving_points":7,"raw_distance_m":3865.7,"mileage_delta_m":4100.0},"points":[{"lon":120.156067,"lat":30.261812,"locatetime":1778157614000,"time":"2026-05-07 20:40:14","speed":17.5,"mileage":234815.0},{"lon":120.157127,"lat":30.260784,"locatetime":1778157724000,"time":"2026-05-07 20:42:04","speed":10.5,"mileage":234815.1},{"lon":120.163025,"lat":30.260759,"locatetime":1778157894000,"time":"2026-05-07 20:44:54","speed":24.5,"mileage":234815.8},{"lon":120.167503,"lat":30.260448,"locatetime":1778158064000,"time":"2026-05-07 20:47:44","speed":33.5,"mileage":234816.2},{"lon":120.179108,"lat":30.260542,"locatetime":1778158334000,"time":"2026-05-07 20:52:14","speed":11.5,"mileage":234817.4},{"lon":120.190071,"lat":30.259998,"locatetime":1778158454000,"time":"2026-05-07 20:54:14","speed":25.5,"mileage":234818.5},{"lon":120.195747,"lat":30.260145,"locatetime":1778158754000,"time":"2026-05-07 20:59:14","speed":22.5,"mileage":234819.1}]}