{"file":"02.csv","job_id":"04225","provider_hints":{"amap":{"correction":"denoise=1,mapmatch=1,attribute=1,threshold=20,mode=driving","recoup":1,"gap":50},"baidu":{"is_processed":1,"process_option":"denoise_grade=5,need_mapmatch=1,transport_mode=driving","supplement_mode":"driving","coord_type_output":"gcj02"}},"source":{"start_time":"2026-05-15 19:03:59","end_time":"2026-05-15 19:16:49","raw_points":7,"moving_points":7,"raw_distance_m":2198.4,"mileage_delta_m":2400.0},"points":[{"lon":120.177841,"lat":30.26034,"locatetime":1778843039000,"time":"2026-05-15 19:03:59","speed":3.0,"mileage":236041.2},{"lon":120.167618,"lat":30.260019,"locatetime":1778843279000,"time":"2026-05-15 19:07:59","speed":11.5,"mileage":236042.3},{"lon":120.16584,"lat":30.260328,"locatetime":1778843409000,"time":"2026-05-15 19:10:09","speed":15.5,"mileage":236042.4},{"lon":120.15966,"lat":30.260532,"locatetime":1778843709000,"time":"2026-05-15 19:15:09","speed":7.0,"mileage":236043.0},{"lon":120.155998,"lat":30.260372,"locatetime":1778843759000,"time":"2026-05-15 19:15:59","speed":14.5,"mileage":236043.4},{"lon":120.155708,"lat":30.260441,"locatetime":1778843779000,"time":"2026-05-15 19:16:19","speed":2.5,"mileage":236043.5},{"lon":120.155693,"lat":30.26104,"locatetime":1778843809000,"time":"2026-05-15 19:16:49","speed":2.0,"mileage":236043.6}]}