{"file":"02.csv","job_id":"04408","provider_hints":{"amap":{"correction":"denoise=1,mapmatch=1,attribute=1,threshold=20,mode=driving","recoup":1,"gap":50},"baidu":{"is_processed":1,"process_option":"denoise_grade=5,need_mapmatch=1,transport_mode=driving","supplement_mode":"driving","coord_type_output":"gcj02"}},"source":{"start_time":"2026-05-21 07:39:42","end_time":"2026-05-21 07:56:12","raw_points":9,"moving_points":9,"raw_distance_m":3323.9,"mileage_delta_m":3500.0},"points":[{"lon":120.19912,"lat":30.272751,"locatetime":1779320382000,"time":"2026-05-21 07:39:42","speed":15.5,"mileage":236860.9},{"lon":120.199562,"lat":30.266596,"locatetime":1779320552000,"time":"2026-05-21 07:42:32","speed":9.5,"mileage":236861.6},{"lon":120.19944,"lat":30.266356,"locatetime":1779320582000,"time":"2026-05-21 07:43:02","speed":24.5,"mileage":236861.7},{"lon":120.196083,"lat":30.266056,"locatetime":1779320742000,"time":"2026-05-21 07:45:42","speed":28.0,"mileage":236862.0},{"lon":120.196022,"lat":30.260296,"locatetime":1779320962000,"time":"2026-05-21 07:49:22","speed":5.0,"mileage":236862.7},{"lon":120.194229,"lat":30.259771,"locatetime":1779321012000,"time":"2026-05-21 07:50:12","speed":11.5,"mileage":236862.9},{"lon":120.193459,"lat":30.259947,"locatetime":1779321102000,"time":"2026-05-21 07:51:42","speed":10.0,"mileage":236862.9},{"lon":120.18615,"lat":30.259857,"locatetime":1779321312000,"time":"2026-05-21 07:55:12","speed":45.0,"mileage":236863.7},{"lon":120.179054,"lat":30.260376,"locatetime":1779321372000,"time":"2026-05-21 07:56:12","speed":25.0,"mileage":236864.4}]}